webifier/__init__.py
webifier/__version__.py
webifier/main.py
webifier/build/__init__.py
webifier/build/builder.py
webifier/build/content.py
webifier/build/html.py
webifier/build/io_utils.py
webifier/build/jekyll.py
webifier/build/md.py
webifier/build/notebook.py
webifier/jekyll/search.json
webifier/jekyll/_includes/chapters.html
webifier/jekyll/_includes/comments.html
webifier/jekyll/_includes/footer.html
webifier/jekyll/_includes/head.html
webifier/jekyll/_includes/header.html
webifier/jekyll/_includes/link.html
webifier/jekyll/_includes/links.html
webifier/jekyll/_includes/meta.html
webifier/jekyll/_includes/nav.html
webifier/jekyll/_includes/people.html
webifier/jekyll/_includes/person.html
webifier/jekyll/_includes/search.html
webifier/jekyll/_includes/toc.html
webifier/jekyll/_layouts/content.html
webifier/jekyll/_layouts/home.html
webifier/jekyll/assets/css/codehilite.css
webifier/jekyll/assets/css/jupyter.css
webifier/jekyll/assets/css/main.css
webifier/jekyll/assets/images/colab-badge.svg
webifier-0.1.20.dist-info/LICENSE
webifier-0.1.20.dist-info/METADATA
webifier-0.1.20.dist-info/WHEEL
webifier-0.1.20.dist-info/entry_points.txt
webifier-0.1.20.dist-info/top_level.txt
webifier-0.1.20.dist-info/RECORD
