Metadata-Version: 2.1
Name: webifier
Version: 0.1.20
Summary: Cook up a fully functional (semi-)static website to be served with jekyll!
Home-page: https://github.com/webifier/build
Author: Vahid Zehtab, Ahmad Salimi
Author-email: vahid98zee@gmail.com, ahsa9978@gmail.com
License: MIT
Keywords: webifier,jupyter notebook,markdown,jekyll
Platform: UNKNOWN
Classifier: Development Status :: 3 - Alpha
Classifier: Intended Audience :: Developers
Classifier: License :: OSI Approved :: MIT License
Classifier: Programming Language :: Python :: 3.8
Requires-Dist: ipython-genutils
Requires-Dist: nbconvert ==5.6.1
Requires-Dist: beautifulsoup4
Requires-Dist: pyyaml
Requires-Dist: ipython
Requires-Dist: Pygments
Requires-Dist: Markdown
Requires-Dist: jinja2 ==3.0.3
